<?xml version="1.0" encoding="utf-8" ?>
<dwsync>
<file name="background.gif" server="192.168.10.26//websites/www.vrbmarketing.com2/" local="129624330194025559" remote="130516550400000000" Dst="2" />
<file name="button.gif" server="192.168.10.26//websites/www.vrbmarketing.com2/" local="129624330194181805" remote="130516550400000000" Dst="2" />
<file name="icon_font.gif" server="192.168.10.26//websites/www.vrbmarketing.com2/" local="129624330194494297" remote="130516550400000000" Dst="2" />
<file name="icon_print.gif" server="192.168.10.26//websites/www.vrbmarketing.com2/" local="129624330194650543" remote="130516550400000000" Dst="2" />
<file name="icon_sound.gif" server="192.168.10.26//websites/www.vrbmarketing.com2/" local="129624330194806789" remote="130516550400000000" Dst="2" />
<file name="innershadow.gif" server="192.168.10.26//websites/www.vrbmarketing.com2/" local="129624330195119281" remote="130516550400000000" Dst="2" />
<file name="logo.gif" server="192.168.10.26//websites/www.vrbmarketing.com2/" local="129624330195275527" remote="130516550400000000" Dst="2" />
<file name="tabs_left.gif" server="192.168.10.26//websites/www.vrbmarketing.com2/" local="129624330195431773" remote="130516550400000000" Dst="2" />
<file name="tabs_right.gif" server="192.168.10.26//websites/www.vrbmarketing.com2/" local="129624330195588019" remote="130516550400000000" Dst="2" />
<file name="button.gif" server="192.168.10.26/websites/www.vrbmarketing.com/" local="129624330194181805" remote="131329000800000000" Dst="1" />
<file name="icon_sound.gif" server="192.168.10.26/websites/www.vrbmarketing.com/" local="129624330194806789" remote="131329000800000000" Dst="1" />
<file name="tabs_left.gif" server="192.168.10.26/websites/www.vrbmarketing.com/" local="129624330195431773" remote="131329000800000000" Dst="1" />
<file name="icon_print.gif" server="192.168.10.26/websites/www.vrbmarketing.com/" local="129624330194650543" remote="131329000800000000" Dst="1" />
<file name="innershadow.gif" server="192.168.10.26/websites/www.vrbmarketing.com/" local="129624330195119281" remote="131329000800000000" Dst="1" />
<file name="background.gif" server="192.168.10.26/websites/www.vrbmarketing.com/" local="129624330194025559" remote="131329000800000000" Dst="1" />
<file name="tabs_right.gif" server="192.168.10.26/websites/www.vrbmarketing.com/" local="129624330195588019" remote="131329000800000000" Dst="1" />
<file name="icon_font.gif" server="192.168.10.26/websites/www.vrbmarketing.com/" local="129624330194494297" remote="131329000800000000" Dst="1" />
<file name="logo.gif" server="192.168.10.26/websites/www.vrbmarketing.com/" local="129624330195275527" remote="131329000800000000" Dst="1" />
</dwsync>