<tweets>
  <tweet>
    <id>1827480949354815884</id>
    <text>LOVE WHERE IM FROM! https://t.co/kf8V2MXPM0</text>
    <source></source>
    <date>2024-08-24 22:59:45</date>
    <user>1064042478</user>
    <image>https://pbs.twimg.com/profile_images/1665426549464612864/IqDQ-mt-_normal.jpg</image>
  </tweet>
  <tweet>
    <id>1827514823996743932</id>
    <text>HAVE A DAY!! YOU STILL GOT IT BLOOD @Tljefferson23</text>
    <source></source>
    <date>2024-08-25 01:14:22</date>
    <user>1064042478</user>
    <image>https://pbs.twimg.com/profile_images/1665426549464612864/IqDQ-mt-_normal.jpg</image>
  </tweet>
  <tweet>
    <id>1827890139802046771</id>
    <text>I’m ready for some @Saints football !! 

If you are a real saints fan, share this tweet for a chance to sit in my suite with my family for first home game against Carolina https://t.co/VzMjyTMocb</text>
    <source></source>
    <date>2024-08-26 02:05:44</date>
    <user>1064042478</user>
    <image>https://pbs.twimg.com/profile_images/1665426549464612864/IqDQ-mt-_normal.jpg</image>
  </tweet>
  <tweet>
    <id>1828057641865695602</id>
    <text>I’ll announce the two winners today! Make sure you are following me and the @saints 

&#38;amp; yes, I’m selecting two people! https://t.co/Nv9N9YFkcK</text>
    <source></source>
    <date>2024-08-26 13:11:20</date>
    <user>1064042478</user>
    <image>https://pbs.twimg.com/profile_images/1665426549464612864/IqDQ-mt-_normal.jpg</image>
  </tweet>
  <tweet>
    <id>1828119609993765122</id>
    <text>RT @LSUfootball: The New Tyrann Mathieu Players’ Lounge 

7 | @Mathieu_Era https://t.co/jALc7TPrzk</text>
    <source></source>
    <date>2024-08-26 17:17:34</date>
    <user>1064042478</user>
    <image>https://pbs.twimg.com/profile_images/1665426549464612864/IqDQ-mt-_normal.jpg</image>
  </tweet>
  <tweet>
    <id>1828172074084639055</id>
    <text>Congrats to the winners @bpj4410 &#38;amp; @Think_igaf 

Looking forward to seeing you guys week one at home!!! The suite is going to be rocking, bring your passion we will need it!</text>
    <source></source>
    <date>2024-08-26 20:46:02</date>
    <user>1064042478</user>
    <image>https://pbs.twimg.com/profile_images/1665426549464612864/IqDQ-mt-_normal.jpg</image>
  </tweet>
  <tweet>
    <id>1828410782339457147</id>
    <text>Do it for you 💪🏽 https://t.co/pfkkJt1yRl</text>
    <source></source>
    <date>2024-08-27 12:34:35</date>
    <user>1064042478</user>
    <image>https://pbs.twimg.com/profile_images/1665426549464612864/IqDQ-mt-_normal.jpg</image>
  </tweet>
  <tweet>
    <id>1828468892072636772</id>
    <text>They got dudes who will make the team that ain’t put nothing into it &#38;amp; dudes who gave it their all will go home! It’s always a sad day!</text>
    <source></source>
    <date>2024-08-27 16:25:29</date>
    <user>1064042478</user>
    <image>https://pbs.twimg.com/profile_images/1665426549464612864/IqDQ-mt-_normal.jpg</image>
  </tweet>
  <tweet>
    <id>1828477326042243157</id>
    <text>Yall be tweaking.</text>
    <source></source>
    <date>2024-08-27 16:59:00</date>
    <user>1064042478</user>
    <image>https://pbs.twimg.com/profile_images/1665426549464612864/IqDQ-mt-_normal.jpg</image>
  </tweet>
  <tweet>
    <id>1828556594919170169</id>
    <text>Almost time to prove my point again. #Ready</text>
    <source></source>
    <date>2024-08-27 22:13:59</date>
    <user>1064042478</user>
    <image>https://pbs.twimg.com/profile_images/1665426549464612864/IqDQ-mt-_normal.jpg</image>
  </tweet>
  <tweet>
    <id>1828629359613169690</id>
    <text>RT @JPowers25: “I’m not no yes man….im loyal…and I stand on what I stand on”</text>
    <source></source>
    <date>2024-08-28 03:03:08</date>
    <user>1064042478</user>
    <image>https://pbs.twimg.com/profile_images/1665426549464612864/IqDQ-mt-_normal.jpg</image>
  </tweet>
  <tweet>
    <id>1828815391402950973</id>
    <text>Keep Geauxing https://t.co/qlqkGkCE2o</text>
    <source></source>
    <date>2024-08-28 15:22:21</date>
    <user>1064042478</user>
    <image>https://pbs.twimg.com/profile_images/1665426549464612864/IqDQ-mt-_normal.jpg</image>
  </tweet>
  <tweet>
    <id>1828984395463536928</id>
    <text>Got mines today🔥🔥🔥🔥 
Lou the best!! https://t.co/lnEJoQXPHA</text>
    <source></source>
    <date>2024-08-29 02:33:55</date>
    <user>1064042478</user>
    <image>https://pbs.twimg.com/profile_images/1665426549464612864/IqDQ-mt-_normal.jpg</image>
  </tweet>
  <tweet>
    <id>1829219831054258221</id>
    <text>⚜️💪🏽 https://t.co/GzlAoLpRb8</text>
    <source></source>
    <date>2024-08-29 18:09:27</date>
    <user>1064042478</user>
    <image>https://pbs.twimg.com/profile_images/1665426549464612864/IqDQ-mt-_normal.jpg</image>
  </tweet>
  <tweet>
    <id>1829226671582400894</id>
    <text>The kid can play! He will be around a while https://t.co/C2A3YD33Z2</text>
    <source></source>
    <date>2024-08-29 18:36:38</date>
    <user>1064042478</user>
    <image>https://pbs.twimg.com/profile_images/1665426549464612864/IqDQ-mt-_normal.jpg</image>
  </tweet>
  <tweet>
    <id>1829955679052054928</id>
    <text>🙏🙏🙏💪🏽 https://t.co/cwgj6Hj1Ux</text>
    <source></source>
    <date>2024-08-31 18:53:27</date>
    <user>1064042478</user>
    <image>https://pbs.twimg.com/profile_images/1665426549464612864/IqDQ-mt-_normal.jpg</image>
  </tweet>
  <tweet>
    <id>1830397859084075018</id>
    <text>Let’s Geaux Cubs!!!! I see you big T, you make dad proud always! https://t.co/wDP732TSe5</text>
    <source></source>
    <date>2024-09-02 00:10:31</date>
    <user>1064042478</user>
    <image>https://pbs.twimg.com/profile_images/1665426549464612864/IqDQ-mt-_normal.jpg</image>
  </tweet>
  <tweet>
    <id>1830605486573731855</id>
    <text>FOREVER LSU!</text>
    <source></source>
    <date>2024-09-02 13:55:33</date>
    <user>1064042478</user>
    <image>https://pbs.twimg.com/profile_images/1665426549464612864/IqDQ-mt-_normal.jpg</image>
  </tweet>
  <tweet>
    <id>1830605643738501456</id>
    <text>I still believe!!! 
HOW BAD DO WE WANT IT?. LETS GEAUX 
@LSUfootball</text>
    <source></source>
    <date>2024-09-02 13:56:11</date>
    <user>1064042478</user>
    <image>https://pbs.twimg.com/profile_images/1665426549464612864/IqDQ-mt-_normal.jpg</image>
  </tweet>
  <tweet>
    <id>1830698088995881197</id>
    <text>My kids love me!!!</text>
    <source></source>
    <date>2024-09-02 20:03:31</date>
    <user>1064042478</user>
    <image>https://pbs.twimg.com/profile_images/1665426549464612864/IqDQ-mt-_normal.jpg</image>
  </tweet>
  <tweet>
    <id>1842934718121263167</id>
    <text>Coming to town putting it down I ain’t lost it ——— ⚜️ https://t.co/WUjaL4bMlX</text>
    <source></source>
    <date>2024-10-06 14:27:31</date>
    <user>1064042478</user>
    <image>https://pbs.twimg.com/profile_images/1665426549464612864/IqDQ-mt-_normal.jpg</image>
  </tweet>
  <tweet>
    <id>1843074757144809697</id>
    <text>❤️❤️❤️ https://t.co/MoTPe75CAy</text>
    <source></source>
    <date>2024-10-06 23:43:59</date>
    <user>1064042478</user>
    <image>https://pbs.twimg.com/profile_images/1665426549464612864/IqDQ-mt-_normal.jpg</image>
  </tweet>
  <tweet>
    <id>1845117086177091956</id>
    <text>I OWE THE GAME, THE GAME DON’T OWE ME!! #HighlyCommitted https://t.co/72Kn7OUQBA</text>
    <source></source>
    <date>2024-10-12 14:59:28</date>
    <user>1064042478</user>
    <image>https://pbs.twimg.com/profile_images/1665426549464612864/IqDQ-mt-_normal.jpg</image>
  </tweet>
  <tweet>
    <id>1845250213381812283</id>
    <text>@ChrisHarrisJr Congrats bro!!!</text>
    <source></source>
    <date>2024-10-12 23:48:28</date>
    <user>1064042478</user>
    <image>https://pbs.twimg.com/profile_images/1665426549464612864/IqDQ-mt-_normal.jpg</image>
  </tweet>
  <tweet>
    <id>1845973760832057532</id>
    <text>@JohnathanAbram1 More glory</text>
    <source></source>
    <date>2024-10-14 23:43:35</date>
    <user>1064042478</user>
    <image>https://pbs.twimg.com/profile_images/1665426549464612864/IqDQ-mt-_normal.jpg</image>
  </tweet>
  <tweet>
    <id>1846222538109554972</id>
    <text>It’s now or never!!!</text>
    <source></source>
    <date>2024-10-15 16:12:08</date>
    <user>1064042478</user>
    <image>https://pbs.twimg.com/profile_images/1665426549464612864/IqDQ-mt-_normal.jpg</image>
  </tweet>
</tweets>