<tweets>
  <tweet>
    <id>1828448797837381638</id>
    <text>RT @MiamiDolphins: Today we remember and honor the life and legacy of Jason Jenkins, a leader, advocate, trailblazer and friend.

We miss y…</text>
    <source></source>
    <date>2024-08-27 15:05:38</date>
    <user>233086747</user>
    <image>https://pbs.twimg.com/profile_images/1764749380102287360/G2OI8xIM_normal.jpg</image>
  </tweet>
  <tweet>
    <id>1828518661436416073</id>
    <text>Training camp 9 🫡</text>
    <source></source>
    <date>2024-08-27 19:43:15</date>
    <user>233086747</user>
    <image>https://pbs.twimg.com/profile_images/1764749380102287360/G2OI8xIM_normal.jpg</image>
  </tweet>
  <tweet>
    <id>1828604035756069216</id>
    <text>RT @MiamiDolphins: Our song: 53-man edition 🎶🌴 https://t.co/yo19Uv645e</text>
    <source></source>
    <date>2024-08-28 01:22:30</date>
    <user>233086747</user>
    <image>https://pbs.twimg.com/profile_images/1764749380102287360/G2OI8xIM_normal.jpg</image>
  </tweet>
  <tweet>
    <id>1831092225599848484</id>
    <text>Cowboy Legend 🫡 https://t.co/2KIQfOlz2J</text>
    <source></source>
    <date>2024-09-03 22:09:41</date>
    <user>233086747</user>
    <image>https://pbs.twimg.com/profile_images/1764749380102287360/G2OI8xIM_normal.jpg</image>
  </tweet>
</tweets>