<tweets>
  <tweet>
    <id>1842638035352981506</id>
    <text>RT @NewManchesterFB: Greison McKelvey
( @_GMck4_ )
2025
DB
5’8 160
3.2 gpa
4707554955
Mid season https://t.co/X6rj48nQXi

Track &#38;amp; field guy…</text>
    <source></source>
    <date>2024-10-05 18:48:36</date>
    <user>2375986764</user>
    <image>https://pbs.twimg.com/profile_images/1692163450250661888/WAngKxWg_normal.jpg</image>
  </tweet>
  <tweet>
    <id>1843340958844498320</id>
    <text>Coach 🅿️ For Now ⏰👀 https://t.co/ofAhQjU3eJ</text>
    <source></source>
    <date>2024-10-07 17:21:46</date>
    <user>2375986764</user>
    <image>https://pbs.twimg.com/profile_images/1692163450250661888/WAngKxWg_normal.jpg</image>
  </tweet>
  <tweet>
    <id>1843681912575144259</id>
    <text>RT @AUbarn_Byotch: It absolutely doesn’t matter where you stand on a particular political issue and it doesn’t matter who contacted who fir…</text>
    <source></source>
    <date>2024-10-08 15:56:36</date>
    <user>2375986764</user>
    <image>https://pbs.twimg.com/profile_images/1692163450250661888/WAngKxWg_normal.jpg</image>
  </tweet>
</tweets>