<tweets>
  <tweet>
    <id>1845868210379256182</id>
    <text>RT @Shtreetwear: BAPE x Pepsi (2001) https://t.co/47uA7foSLu</text>
    <source></source>
    <date>2024-10-14 16:44:10</date>
    <user>3169334760</user>
    <image>https://pbs.twimg.com/profile_images/1820230754401505280/NpwofBtz_normal.jpg</image>
  </tweet>
  <tweet>
    <id>1845887232160551055</id>
    <text>Gangstaaaa https://t.co/wZl3DChwgF</text>
    <source></source>
    <date>2024-10-14 17:59:45</date>
    <user>3169334760</user>
    <image>https://pbs.twimg.com/profile_images/1820230754401505280/NpwofBtz_normal.jpg</image>
  </tweet>
  <tweet>
    <id>1845953188605657340</id>
    <text>RT @MobbinBilly93: Be careful who you putting first , you just might be last to them ..</text>
    <source></source>
    <date>2024-10-14 22:21:50</date>
    <user>3169334760</user>
    <image>https://pbs.twimg.com/profile_images/1820230754401505280/NpwofBtz_normal.jpg</image>
  </tweet>
  <tweet>
    <id>1845953384266047545</id>
    <text>Got cut in these streets from young for having a big heart never again</text>
    <source></source>
    <date>2024-10-14 22:22:37</date>
    <user>3169334760</user>
    <image>https://pbs.twimg.com/profile_images/1820230754401505280/NpwofBtz_normal.jpg</image>
  </tweet>
  <tweet>
    <id>1845953426657890337</id>
    <text>RT @MobbinBilly93: Never trust your tongue when your heart is hurt, Hush until you heal..</text>
    <source></source>
    <date>2024-10-14 22:22:47</date>
    <user>3169334760</user>
    <image>https://pbs.twimg.com/profile_images/1820230754401505280/NpwofBtz_normal.jpg</image>
  </tweet>
  <tweet>
    <id>1845953455447232989</id>
    <text>RT @ionfeellnun: Ion even get mad no more I just get the hell on</text>
    <source></source>
    <date>2024-10-14 22:22:54</date>
    <user>3169334760</user>
    <image>https://pbs.twimg.com/profile_images/1820230754401505280/NpwofBtz_normal.jpg</image>
  </tweet>
  <tweet>
    <id>1845953879273247000</id>
    <text>Who masters patience can master anything</text>
    <source></source>
    <date>2024-10-14 22:24:35</date>
    <user>3169334760</user>
    <image>https://pbs.twimg.com/profile_images/1820230754401505280/NpwofBtz_normal.jpg</image>
  </tweet>
  <tweet>
    <id>1845953930645459271</id>
    <text>RT @KdNeph: i know the game so ion trip</text>
    <source></source>
    <date>2024-10-14 22:24:47</date>
    <user>3169334760</user>
    <image>https://pbs.twimg.com/profile_images/1820230754401505280/NpwofBtz_normal.jpg</image>
  </tweet>
  <tweet>
    <id>1845953979521376315</id>
    <text>RT @MobbinBilly93: 3 N’s: NEVER NEEDED NOBODY ..</text>
    <source></source>
    <date>2024-10-14 22:24:59</date>
    <user>3169334760</user>
    <image>https://pbs.twimg.com/profile_images/1820230754401505280/NpwofBtz_normal.jpg</image>
  </tweet>
  <tweet>
    <id>1845954001675694340</id>
    <text>RT @datsCaspr: Kinda glad I go thru alot, it's making me a monster.
💯</text>
    <source></source>
    <date>2024-10-14 22:25:04</date>
    <user>3169334760</user>
    <image>https://pbs.twimg.com/profile_images/1820230754401505280/NpwofBtz_normal.jpg</image>
  </tweet>
  <tweet>
    <id>1845954020961120455</id>
    <text>RT @Flashyasf: I was slacking but I’m back in that mode</text>
    <source></source>
    <date>2024-10-14 22:25:09</date>
    <user>3169334760</user>
    <image>https://pbs.twimg.com/profile_images/1820230754401505280/NpwofBtz_normal.jpg</image>
  </tweet>
  <tweet>
    <id>1845955035571630283</id>
    <text>RT @Flashyasf: They might not fw you but they watching tho 😂</text>
    <source></source>
    <date>2024-10-14 22:29:11</date>
    <user>3169334760</user>
    <image>https://pbs.twimg.com/profile_images/1820230754401505280/NpwofBtz_normal.jpg</image>
  </tweet>
  <tweet>
    <id>1845955172045828128</id>
    <text>RT @only4be: I saw it I just ain’t say none</text>
    <source></source>
    <date>2024-10-14 22:29:43</date>
    <user>3169334760</user>
    <image>https://pbs.twimg.com/profile_images/1820230754401505280/NpwofBtz_normal.jpg</image>
  </tweet>
  <tweet>
    <id>1845955266225090846</id>
    <text>RT @papidevoo: this road lonely but ik god got me</text>
    <source></source>
    <date>2024-10-14 22:30:06</date>
    <user>3169334760</user>
    <image>https://pbs.twimg.com/profile_images/1820230754401505280/NpwofBtz_normal.jpg</image>
  </tweet>
  <tweet>
    <id>1845955288626507817</id>
    <text>RT @h8tejay: trust on -0</text>
    <source></source>
    <date>2024-10-14 22:30:11</date>
    <user>3169334760</user>
    <image>https://pbs.twimg.com/profile_images/1820230754401505280/NpwofBtz_normal.jpg</image>
  </tweet>
  <tweet>
    <id>1845956136740049378</id>
    <text>RT @datsCaspr: Been going thru a lil storm by myself lately..... but watch how I come out tho ‼️💪</text>
    <source></source>
    <date>2024-10-14 22:33:33</date>
    <user>3169334760</user>
    <image>https://pbs.twimg.com/profile_images/1820230754401505280/NpwofBtz_normal.jpg</image>
  </tweet>
  <tweet>
    <id>1846193768669593662</id>
    <text>All I know is go hard</text>
    <source></source>
    <date>2024-10-15 14:17:49</date>
    <user>3169334760</user>
    <image>https://pbs.twimg.com/profile_images/1820230754401505280/NpwofBtz_normal.jpg</image>
  </tweet>
  <tweet>
    <id>1846210230641623159</id>
    <text>RT @ionfeellnun: I ain’t forcing shit but a rubber band around some money</text>
    <source></source>
    <date>2024-10-15 15:23:14</date>
    <user>3169334760</user>
    <image>https://pbs.twimg.com/profile_images/1820230754401505280/NpwofBtz_normal.jpg</image>
  </tweet>
  <tweet>
    <id>1846300126119448697</id>
    <text>RT @ionfeellnun: Keep grinding you gone get it</text>
    <source></source>
    <date>2024-10-15 21:20:27</date>
    <user>3169334760</user>
    <image>https://pbs.twimg.com/profile_images/1820230754401505280/NpwofBtz_normal.jpg</image>
  </tweet>
  <tweet>
    <id>1846300209636077891</id>
    <text>Money for these wars</text>
    <source></source>
    <date>2024-10-15 21:20:47</date>
    <user>3169334760</user>
    <image>https://pbs.twimg.com/profile_images/1820230754401505280/NpwofBtz_normal.jpg</image>
  </tweet>
  <tweet>
    <id>1846301397194821670</id>
    <text>Took my lessons just stay out my way</text>
    <source></source>
    <date>2024-10-15 21:25:30</date>
    <user>3169334760</user>
    <image>https://pbs.twimg.com/profile_images/1820230754401505280/NpwofBtz_normal.jpg</image>
  </tweet>
  <tweet>
    <id>1846303588207014101</id>
    <text>RT @4lilce: when i stop giving a fuck .. u gone feel it</text>
    <source></source>
    <date>2024-10-15 21:34:12</date>
    <user>3169334760</user>
    <image>https://pbs.twimg.com/profile_images/1820230754401505280/NpwofBtz_normal.jpg</image>
  </tweet>
  <tweet>
    <id>1846303933305663631</id>
    <text>Went back to how I use to be</text>
    <source></source>
    <date>2024-10-15 21:35:35</date>
    <user>3169334760</user>
    <image>https://pbs.twimg.com/profile_images/1820230754401505280/NpwofBtz_normal.jpg</image>
  </tweet>
  <tweet>
    <id>1846304360420331986</id>
    <text>I’m the one I been missing</text>
    <source></source>
    <date>2024-10-15 21:37:16</date>
    <user>3169334760</user>
    <image>https://pbs.twimg.com/profile_images/1820230754401505280/NpwofBtz_normal.jpg</image>
  </tweet>
  <tweet>
    <id>1846305777297784978</id>
    <text>Direction&#38;gt;speed</text>
    <source></source>
    <date>2024-10-15 21:42:54</date>
    <user>3169334760</user>
    <image>https://pbs.twimg.com/profile_images/1820230754401505280/NpwofBtz_normal.jpg</image>
  </tweet>
  <tweet>
    <id>1846649373079621809</id>
    <text>I got lit by myself didn’t need nobody</text>
    <source></source>
    <date>2024-10-16 20:28:14</date>
    <user>3169334760</user>
    <image>https://pbs.twimg.com/profile_images/1820230754401505280/NpwofBtz_normal.jpg</image>
  </tweet>
</tweets>