<tweets>
  <tweet>
    <id>1829347839920504980</id>
    <text>RT @NostalgiaFolder: Danny Phantom (2004-2007) https://t.co/0l8wL4BIJt</text>
    <source></source>
    <date>2024-08-30 02:38:07</date>
    <user>411772772</user>
    <image>https://pbs.twimg.com/profile_images/1631525961224142848/nqDk-1KK_normal.jpg</image>
  </tweet>
  <tweet>
    <id>1829590556886040638</id>
    <text>🪬 😁</text>
    <source></source>
    <date>2024-08-30 18:42:35</date>
    <user>411772772</user>
    <image>https://pbs.twimg.com/profile_images/1631525961224142848/nqDk-1KK_normal.jpg</image>
  </tweet>
  <tweet>
    <id>1830416357994778700</id>
    <text>RT @RGIII: In order to find peace you have to let go of your plan for your life and accept God’s plan even when you don’t understand it. Hi…</text>
    <source></source>
    <date>2024-09-02 01:24:01</date>
    <user>411772772</user>
    <image>https://pbs.twimg.com/profile_images/1631525961224142848/nqDk-1KK_normal.jpg</image>
  </tweet>
</tweets>