<tweets>
  <tweet>
    <id>1827047946388455821</id>
    <text>Gifted myself another watch. Well
Deserved present https://t.co/oZw3QdpOY3</text>
    <source></source>
    <date>2024-08-23 18:19:09</date>
    <user>46257156</user>
    <image>https://pbs.twimg.com/profile_images/1758261403650064384/ZtkOs8KA_normal.jpg</image>
  </tweet>
  <tweet>
    <id>1829912494527160715</id>
    <text>I have a question for you. 
In 2010, I was invited to have a wax figure created of myself at Madame Tussauds in London. However, my friend Sajeed, who was working for my management company at the time, turned down the opportunity. He mentioned that, as Muslims, we should not… https://t.co/bc2e0CJ7H9 https://t.co/HlX3LcB1up</text>
    <source></source>
    <date>2024-08-31 16:01:51</date>
    <user>46257156</user>
    <image>https://pbs.twimg.com/profile_images/1758261403650064384/ZtkOs8KA_normal.jpg</image>
  </tweet>
  <tweet>
    <id>1830928409368654153</id>
    <text>Good morning y’all https://t.co/N20gr0PWMB</text>
    <source></source>
    <date>2024-09-03 11:18:44</date>
    <user>46257156</user>
    <image>https://pbs.twimg.com/profile_images/1758261403650064384/ZtkOs8KA_normal.jpg</image>
  </tweet>
  <tweet>
    <id>1844289772384288955</id>
    <text>Look who I’m sat next to @FawadNaeemRana @lahoreqalandars  #PSL https://t.co/g5GXcuHtu3</text>
    <source></source>
    <date>2024-10-10 08:12:01</date>
    <user>46257156</user>
    <image>https://pbs.twimg.com/profile_images/1758261403650064384/ZtkOs8KA_normal.jpg</image>
  </tweet>
  <tweet>
    <id>1845080444053737974</id>
    <text>RT @Queensberry: Could we see @amirkingkhan return to the ring against the great @MannyPacquiao? 👀

Catch our exclusive interviews with all…</text>
    <source></source>
    <date>2024-10-12 12:33:52</date>
    <user>46257156</user>
    <image>https://pbs.twimg.com/profile_images/1758261403650064384/ZtkOs8KA_normal.jpg</image>
  </tweet>
  <tweet>
    <id>1845224738525782448</id>
    <text>A game of chess #BivolBeterbiev https://t.co/xl8QHGdbPB</text>
    <source></source>
    <date>2024-10-12 22:07:14</date>
    <user>46257156</user>
    <image>https://pbs.twimg.com/profile_images/1758261403650064384/ZtkOs8KA_normal.jpg</image>
  </tweet>
  <tweet>
    <id>1845230004067520918</id>
    <text>RT @DAZNBoxing: Olympic silver medalist in the ring as another arrives 🥈 @amirkingkhan 

#BeterbievBivol | #RiyadhSeason | Oct 12, live NOW…</text>
    <source></source>
    <date>2024-10-12 22:28:10</date>
    <user>46257156</user>
    <image>https://pbs.twimg.com/profile_images/1758261403650064384/ZtkOs8KA_normal.jpg</image>
  </tweet>
  <tweet>
    <id>1845244566288363944</id>
    <text>Alhamdulilah our Muslim brother becomes undisputed champion @RiyadhSeason @Turki_alalshikh https://t.co/6yAjEJwwr3</text>
    <source></source>
    <date>2024-10-12 23:26:02</date>
    <user>46257156</user>
    <image>https://pbs.twimg.com/profile_images/1758261403650064384/ZtkOs8KA_normal.jpg</image>
  </tweet>
  <tweet>
    <id>1845415026779095349</id>
    <text>As #BeterbievBivol fought I kept the 
  IBF title warm for the winner https://t.co/S5ErAx8NSu</text>
    <source></source>
    <date>2024-10-13 10:43:23</date>
    <user>46257156</user>
    <image>https://pbs.twimg.com/profile_images/1758261403650064384/ZtkOs8KA_normal.jpg</image>
  </tweet>
  <tweet>
    <id>1846213657111285773</id>
    <text>https://t.co/xz9xG44hGw</text>
    <source></source>
    <date>2024-10-15 15:36:51</date>
    <user>46257156</user>
    <image>https://pbs.twimg.com/profile_images/1758261403650064384/ZtkOs8KA_normal.jpg</image>
  </tweet>
  <tweet>
    <id>1846576497689039027</id>
    <text>RT @ProBoxingFans: "𝗙𝗶𝗿𝘀𝘁 𝘁𝗶𝗺𝗲 𝘄𝗮𝘁𝗰𝗵𝗶𝗻𝗴 𝗵𝗶𝗺.. 𝘄𝗵𝗮𝘁 𝗮 𝗕𝗘𝗔𝗦𝗧!" 😱

Safe to say @amirkingkhan was impressed with Artur Beterbiev's display on S…</text>
    <source></source>
    <date>2024-10-16 15:38:39</date>
    <user>46257156</user>
    <image>https://pbs.twimg.com/profile_images/1758261403650064384/ZtkOs8KA_normal.jpg</image>
  </tweet>
</tweets>