<tweets>
  <tweet>
    <id>439908736300089344</id>
    <text>Got all the nerves and butterflies out today during my first Cactus League action. True test for my knee.. #confidencewentwayup #imgood</text>
    <source></source>
    <date>Sat Mar 01 23:43:10 +0000 2014</date>
    <user>464042992</user>
    <image>http://pbs.twimg.com/profile_images/424011655723618304/NcNPzYyE_normal.jpeg</image>
  </tweet>
  <tweet>
    <id>439929504899665920</id>
    <text>RT @Godly_Life: Be anxious for nothing, but in everything by prayer and supplication with thanksgiving let your requests be made known to G…</text>
    <source></source>
    <date>Sun Mar 02 01:05:42 +0000 2014</date>
    <user>464042992</user>
    <image>http://pbs.twimg.com/profile_images/424011655723618304/NcNPzYyE_normal.jpeg</image>
  </tweet>
</tweets>