<tweets>
  <tweet>
    <id>1830767233335009364</id>
    <text>TAKE HIM OUT !!!</text>
    <source></source>
    <date>2024-09-03 00:38:17</date>
    <user>72351148</user>
    <image>https://pbs.twimg.com/profile_images/1246737324580524032/RMgkzn3s_normal.jpg</image>
  </tweet>
  <tweet>
    <id>1830773239242727498</id>
    <text>BRUHHHH WTF</text>
    <source></source>
    <date>2024-09-03 01:02:09</date>
    <user>72351148</user>
    <image>https://pbs.twimg.com/profile_images/1246737324580524032/RMgkzn3s_normal.jpg</image>
  </tweet>
  <tweet>
    <id>1830785369006293155</id>
    <text>AND THEM BIG D TACKLES NOT AS ADVERTISED</text>
    <source></source>
    <date>2024-09-03 01:50:20</date>
    <user>72351148</user>
    <image>https://pbs.twimg.com/profile_images/1246737324580524032/RMgkzn3s_normal.jpg</image>
  </tweet>
  <tweet>
    <id>1843698220763173087</id>
    <text>Mets Yanks 👀 https://t.co/Lom7i0sJda</text>
    <source></source>
    <date>2024-10-08 17:01:24</date>
    <user>72351148</user>
    <image>https://pbs.twimg.com/profile_images/1246737324580524032/RMgkzn3s_normal.jpg</image>
  </tweet>
</tweets>